README.md
setup.cfg
setup.py
ker_dict_tools/__init__.py
ker_dict_tools/dictDiff.py
ker_dict_tools/dictPaths.py
ker_dict_tools.egg-info/PKG-INFO
ker_dict_tools.egg-info/SOURCES.txt
ker_dict_tools.egg-info/dependency_links.txt
ker_dict_tools.egg-info/top_level.txt