Metadata-Version: 2.1
Name: ker-dict-tools
Version: 0.1.1
Summary: Tools for smart operations with python dicts
Home-page: https://bitbucket.org/kerkops/dict_tools
Author: Luca Buccioni
Author-email: kerkops7@gmail.com
License: MIT
Keywords: dicts,dict,path,paths,paths for dicts,dict diff,dict differences,diff,operations on dictionaries,dict values by path,dict queries,dict query,differences between nested dicts,Intended Audience :: Developers,Topic :: Software Development :: Build Tools,License :: OSI Approved :: MIT License,Programming Language :: Python :: 3,Programming Language :: Python :: 3.6,Programming Language :: Python :: 2,Programming Language :: Python :: 2.7
Platform: UNKNOWN
